{
  "// BITW AI Enhancement Suite - Ultimate AI Configuration": "",
  "// Advanced AI Features": "",
  "github.copilot.enable": {
    "*": true,
    "yaml": true,
    "plaintext": true,
    "markdown": true,
    "python": true,
    "javascript": true,
    "typescript": true,
    "json": true,
    "html": true,
    "css": true,
    "scss": true,
    "sql": true,
    "shell": true
  },
  "github.copilot.advanced": {
    "secret_key": "sk-bitw-ai-enhancement",
    "length": 1000,
    "temperature": 0.7,
    "top_p": 1,
    "stop": [
      "###",
      "```"
    ],
    "inlineSuggestCount": 5
  },
  "// Intelligent Code Analysis": "",
  "python.analysis.typeCheckingMode": "strict",
  "python.analysis.autoImportCompletions": true,
  "python.analysis.completeFunctionParens": true,
  "python.analysis.diagnosticMode": "workspace",
  "python.analysis.inlayHints.variableTypes": true,
  "python.analysis.inlayHints.functionReturnTypes": true,
  "python.analysis.inlayHints.callArgumentNames": true,
  "python.analysis.autoFormatStrings": true,
  "// Advanced IntelliSense": "",
  "editor.suggestSelection": "first",
  "editor.tabCompletion": "on",
  "editor.wordBasedSuggestions": "allDocuments",
  "editor.suggest.insertMode": "replace",
  "editor.suggest.preview": true,
  "editor.suggest.showInlineDetails": true,
  "editor.suggest.maxVisibleSuggestions": 15,
  "editor.quickSuggestions": {
    "other": "on",
    "comments": "on",
    "strings": "on"
  },
  "// AI-Powered Error Detection": "",
  "problems.decorations.enabled": true,
  "problems.showCurrentInStatus": true,
  "editor.gotoLocation.multipleReferences": "goto",
  "editor.gotoLocation.multipleDefinitions": "goto",
  "editor.gotoLocation.multipleDeclarations": "goto",
  "// Intelligent Debugging": "",
  "debug.allowBreakpointsEverywhere": true,
  "debug.inlineValues": "auto",
  "debug.showInStatusBar": "always",
  "debug.console.acceptSuggestionOnEnter": "on",
  "// Advanced Git Intelligence": "",
  "git.autofetch": true,
  "git.enableSmartCommit": true,
  "git.suggestSmartCommit": true,
  "git.autoStash": true,
  "gitlens.codeLens.enabled": true,
  "gitlens.currentLine.enabled": true,
  "gitlens.hovers.enabled": true,
  "gitlens.blame.format": "${message|50?} ${agoOrDate|14-}",
  "gitlens.defaultDateFormat": "MMMM Do, YYYY h:mma",
  "// AI Code Formatting": "",
  "editor.formatOnSave": true,
  "editor.formatOnPaste": true,
  "editor.formatOnType": true,
  "editor.codeActionsOnSave": {
    "source.organizeImports": true,
    "source.fixAll": true
  },
  "// Creative AI Features": "",
  "editor.semanticHighlighting.enabled": true,
  "editor.bracketPairColorization.enabled": true,
  "editor.guides.bracketPairs": "active",
  "editor.inlayHints.enabled": "on",
  "editor.lightbulb.enabled": true,
  "// Performance Optimization": "",
  "search.smartCase": true,
  "search.useGlobalIgnoreFiles": true,
  "search.useParentIgnoreFiles": true,
  "files.watcherExclude": {
    "**/.git/objects/**": true,
    "**/.git/subtree-cache/**": true,
    "**/node_modules/*/**": true,
    "**/__pycache__/**": true,
    "**/.pytest_cache/**": true,
    "**/build/**": true,
    "**/dist/**": true
  },
  "// AI Terminal Integration": "",
  "terminal.integrated.suggest.enabled": true,
  "terminal.integrated.shellIntegration.enabled": true,
  "terminal.integrated.enableMultiLinePasteWarning": false,
  "terminal.integrated.rightClickBehavior": "paste",
  "// Workspace Intelligence": "",
  "explorer.confirmDelete": false,
  "explorer.confirmDragAndDrop": false,
  "workbench.editor.enablePreview": false,
  "workbench.editor.revealIfOpen": true,
  "workbench.list.automaticKeyboardNavigation": false,
  "// Advanced Extensions Config": "",
  "extensions.autoCheckUpdates": true,
  "extensions.autoUpdate": true,
  "extensions.ignoreRecommendations": false
}